oneNueron/__init__.py
oneNueron/perceptron.py
oneNueron_pypi_shivanshk1197-0.0.1.dist-info/LICENSE
oneNueron_pypi_shivanshk1197-0.0.1.dist-info/METADATA
oneNueron_pypi_shivanshk1197-0.0.1.dist-info/WHEEL
oneNueron_pypi_shivanshk1197-0.0.1.dist-info/top_level.txt
oneNueron_pypi_shivanshk1197-0.0.1.dist-info/RECORD
