Metadata-Version: 2.1
Name: oneNueron-pypi-shivanshk1197
Version: 0.0.1
Summary: It's an implementation of Perceptron
Home-page: https://github.com/shivanshk1197/oneNueron_pypi
Author: shivanshk1197
Author-email: shivanshk1197@gmail.com
License: UNKNOWN
Project-URL: Bug Tracker, https://github.com/shivanshk1197/oneNueron_pypi/issues
Platform: UNKNOWN
Classifier: Programming Language :: Python :: 3
Classifier: License :: OSI Approved :: MIT License
Classifier: Operating System :: OS Independent
Requires-Python: >=3.7
License-File: LICENSE
Requires-Dist: numpy
Requires-Dist: tqdm
